spellingtest/__init__.py
spellingtest/__main__.py
spellingtest/check.py
spellingtest/version.py
spellingtest-0.2.0.dist-info/LICENSE
spellingtest-0.2.0.dist-info/METADATA
spellingtest-0.2.0.dist-info/WHEEL
spellingtest-0.2.0.dist-info/top_level.txt
spellingtest-0.2.0.dist-info/RECORD
