Metadata-Version: 2.1
Name: spellingtest
Version: 0.2.0
Summary: Utilities for testing pyspelling filters
Home-page: https://github.com/replendent-dev/spellingtest
Author: Tim Gates
Author-email: tim.gates@iress.com
Maintainer: Tim Gates
Maintainer-email: tim.gates@iress.com
License: GPLv3+
Platform: UNKNOWN
Classifier: Development Status :: 4 - Beta
Classifier: Programming Language :: Python
Classifier: Programming Language :: Python :: 3
Classifier: Programming Language :: Python :: 3.4
Classifier: Programming Language :: Python :: 3.5
Classifier: Programming Language :: Python :: 3.6
Classifier: Programming Language :: Python :: 3.7
Classifier: Programming Language :: Python :: Implementation :: CPython
Classifier: Programming Language :: Python :: Implementation :: PyPy
Classifier: Operating System :: OS Independent
Classifier: License :: OSI Approved :: GNU General Public License v3 (GPLv3)
Requires-Python: >=3.4
Requires-Dist: pyspelling
